aifes/__init__.py
aifes/keras2aifes.py
aifes/pytorch2aifes.py
aifes/aifes_code_generator/__init__.py
aifes/aifes_code_generator/aifes_code_creator.py
aifes/aifes_code_generator/support_aifes_code_creator.py
aifes/aifes_code_generator/templates/aifes/aifes_f32_fnn.h
aifes/aifes_code_generator/templates/aifes/aifes_f32_weights.h
aifes/aifes_code_generator/templates/aifes/aifes_q7_fnn.h
aifes/aifes_code_generator/templates/aifes/aifes_q7_weights.h
aifes/aifes_code_generator/templates/aifes_express/aifes_e_f32_fnn.h
aifes/aifes_code_generator/templates/aifes_express/aifes_e_f32_weights.h
aifes/aifes_code_generator/templates/aifes_express/aifes_e_q7_fnn.h
aifes/aifes_code_generator/templates/aifes_express/aifes_e_q7_weights.h
aifes/keras_extractor/__init__.py
aifes/keras_extractor/keras_extractor.py
aifes/model_converter/__init__.py
aifes/model_converter/model_conversion.py
aifes/model_converter/support_model_conversion_q7.py
aifes/pytorch_extractor/__init__.py
aifes/pytorch_extractor/pytorch_extractor.py
aifes/pytorch_extractor/pytorch_extractor_utils.py
aifes/support/__init__.py
aifes/support/aifes_model.py
aifes/support/support_functions.py
AIfES_Converter-1.0.0.dist-info/LICENSE
AIfES_Converter-1.0.0.dist-info/METADATA
AIfES_Converter-1.0.0.dist-info/WHEEL
AIfES_Converter-1.0.0.dist-info/top_level.txt
AIfES_Converter-1.0.0.dist-info/RECORD
